penelope_crypto_tools/__init__.py
penelope_crypto_tools/services/defillama.py
penelope_crypto_tools-0.1.0.dist-info/METADATA
penelope_crypto_tools-0.1.0.dist-info/WHEEL
penelope_crypto_tools-0.1.0.dist-info/entry_points.txt
penelope_crypto_tools-0.1.0.dist-info/RECORD
