Metadata-Version: 2.4
Name: penelope-crypto-tools
Version: 0.1.0
Summary: Package of tools used by Penelope services.
Requires-Python: >=3.10
Requires-Dist: pydantic>=2.11.7
Requires-Dist: requests>=2.32.5
